{"note":"This file is an internal implementation detail to speed up HTML report generation. Its format can change at any time. You might be looking for the JSON report: https://coverage.rtfd.io/cmd.html#cmd-json","format":2,"version":"7.4.2","globals":"731e2be996d2902facd906c4f1248433","files":{"d_508e66bae7ae1f97_list_comparator_py":{"hash":"39d6315e0af41754c948785bec7b9c62","index":{"nums":[0,1,17,0,4,0,0,0],"html_filename":"d_508e66bae7ae1f97_list_comparator_py.html","relative_filename":"D:\\LessonsWork\\Web-developer\\Project\\geekBrains\\Unit-test\\Unit-testsHW6\\list_comparator.py"}},"d_508e66bae7ae1f97_list_stats_py":{"hash":"59530485bae096bea967406e7e2e2563","index":{"nums":[0,1,25,0,4,0,0,0],"html_filename":"d_508e66bae7ae1f97_list_stats_py.html","relative_filename":"D:\\LessonsWork\\Web-developer\\Project\\geekBrains\\Unit-test\\Unit-testsHW6\\list_stats.py"}},"d_508e66bae7ae1f97_main_py":{"hash":"bef66554bd8e291a3918a63ea14d05d5","index":{"nums":[0,1,24,0,12,0,0,0],"html_filename":"d_508e66bae7ae1f97_main_py.html","relative_filename":"D:\\LessonsWork\\Web-developer\\Project\\geekBrains\\Unit-test\\Unit-testsHW6\\main.py"}},"d_508e66bae7ae1f97_run_all_tests_py":{"hash":"3b5c4e81c244c63a370d81dfea011775","index":{"nums":[0,1,11,0,0,0,0,0],"html_filename":"d_508e66bae7ae1f97_run_all_tests_py.html","relative_filename":"D:\\LessonsWork\\Web-developer\\Project\\geekBrains\\Unit-test\\Unit-testsHW6\\run_all_tests.py"}},"d_508e66bae7ae1f97_test_list_comparator_py":{"hash":"df0009c44d50e5b2db1b5e1005226bf7","index":{"nums":[0,1,103,0,9,0,0,0],"html_filename":"d_508e66bae7ae1f97_test_list_comparator_py.html","relative_filename":"D:\\LessonsWork\\Web-developer\\Project\\geekBrains\\Unit-test\\Unit-testsHW6\\test_list_comparator.py"}},"d_508e66bae7ae1f97_test_list_stats_py":{"hash":"13a9fc3e0a62b898ff7e9e4546288a89","index":{"nums":[0,1,20,0,1,0,0,0],"html_filename":"d_508e66bae7ae1f97_test_list_stats_py.html","relative_filename":"D:\\LessonsWork\\Web-developer\\Project\\geekBrains\\Unit-test\\Unit-testsHW6\\test_list_stats.py"}},"d_508e66bae7ae1f97_test_main_py":{"hash":"56aaac684464b4cb57f8481f1831ab49","index":{"nums":[0,1,19,0,1,0,0,0],"html_filename":"d_508e66bae7ae1f97_test_main_py.html","relative_filename":"D:\\LessonsWork\\Web-developer\\Project\\geekBrains\\Unit-test\\Unit-testsHW6\\test_main.py"}}}}